signals/__init__.py
signals/signal.py
signals/functions/__init__.py
signals/functions/baseline.py
signals/functions/function.py
signals/functions/noise.py
signals/perturbations/__init__.py
signals/perturbations/perturbation.py
signals/perturbations/spike_perturbation.py
signals/perturbations/step_perturbation.py
machine_signals-0.0.3.dist-info/LICENSE.txt
machine_signals-0.0.3.dist-info/METADATA
machine_signals-0.0.3.dist-info/WHEEL
machine_signals-0.0.3.dist-info/top_level.txt
machine_signals-0.0.3.dist-info/RECORD
