Metadata-Version: 2.1
Name: machine-signals
Version: 0.0.3
Summary: A simple signals package to create and distort harmonic signals
Home-page: https://github.com/camilorey/signals_package
Author: Camilo Rey-Torres
Author-email: camilorey@gmail.com
License: UNKNOWN
Project-URL: Bug Tracker, https://github.com/camilorey/signals_package/issues
Platform: UNKNOWN
Classifier: Programming Language :: Python :: 3
Classifier: License :: OSI Approved :: MIT License
Classifier: Operating System :: OS Independent
Requires-Python: >=3.6
